esperanto_analyzer/__init__.py
esperanto_analyzer/morphological_sentence_analyzer.py
esperanto_analyzer/analyzers/__init__.py
esperanto_analyzer/analyzers/morphological_analyzer.py
esperanto_analyzer/analyzers/morphological/__init__.py
esperanto_analyzer/analyzers/morphological/adjective.py
esperanto_analyzer/analyzers/morphological/adverb.py
esperanto_analyzer/analyzers/morphological/analyze_result.py
esperanto_analyzer/analyzers/morphological/article.py
esperanto_analyzer/analyzers/morphological/base.py
esperanto_analyzer/analyzers/morphological/conjunction.py
esperanto_analyzer/analyzers/morphological/interjection.py
esperanto_analyzer/analyzers/morphological/noun.py
esperanto_analyzer/analyzers/morphological/numeral.py
esperanto_analyzer/analyzers/morphological/preposition.py
esperanto_analyzer/analyzers/morphological/pronoun.py
esperanto_analyzer/analyzers/morphological/verb.py
esperanto_analyzer/cli/__init__.py
esperanto_analyzer/cli/cli.py
esperanto_analyzer/speech/__init__.py
esperanto_analyzer/speech/adjective.py
esperanto_analyzer/speech/adverb.py
esperanto_analyzer/speech/article.py
esperanto_analyzer/speech/conjunction.py
esperanto_analyzer/speech/interjection.py
esperanto_analyzer/speech/noun.py
esperanto_analyzer/speech/numeral.py
esperanto_analyzer/speech/preposition.py
esperanto_analyzer/speech/pronoun.py
esperanto_analyzer/speech/verb.py
esperanto_analyzer/speech/word.py
esperanto_analyzer/web/__init__.py
esperanto_analyzer/web/context.py
esperanto_analyzer/web/runserver.py
esperanto_analyzer/web/api/__init__.py
esperanto_analyzer/web/api/errors.py
esperanto_analyzer/web/api/helpers.py
esperanto_analyzer/web/api/morphological_endpoint.py
esperanto_analyzer/web/api/resources.py
esperanto_analyzer/web/api/results.py
esperanto_analyzer/web/api/server.py
esperanto_analyzer-0.0.3.dist-info/METADATA
esperanto_analyzer-0.0.3.dist-info/RECORD
esperanto_analyzer-0.0.3.dist-info/WHEEL
esperanto_analyzer-0.0.3.dist-info/top_level.txt
lib/__init__.py
lib/core.py
lib/helpers.py
