Metadata-Version: 2.1
Name: esperanto-analyzer
Version: 0.0.3
Summary: Morphological and syntactic analysis of Esperanto sentences.
Home-page: https://github.com/fidelisrafael/esperanto-analyzer
Author: Rafael Fidelis
Author-email: rafaelfid3lis@gmail.com
License: Copyright (c) 2018, Rafael Fidelis
Requires-Dist: tableprint (==0.8.0)
Requires-Dist: Flask (==1.0.2)
Requires-Dist: Flask-RESTful (==0.3.6)
Requires-Dist: flask-restful-swagger (==0.20.1)
